django_redis_session/__init__.py
django_redis_session/redis_server.py
django_redis_session/session_store.py
django_redis_session/tests.py
django_redis_session-0.1.0.dist-info/LICENSE
django_redis_session-0.1.0.dist-info/METADATA
django_redis_session-0.1.0.dist-info/WHEEL
django_redis_session-0.1.0.dist-info/top_level.txt
django_redis_session-0.1.0.dist-info/RECORD
