Metadata-Version: 2.1
Name: django-redis-session
Version: 0.1.0
Summary: A Django session backend with Redis storage.
Author: Ömer Alkın
Author-email: Ömer Alkın <omeralkin7@gmail.com>
License: MIT License
Project-URL: Home, https://github.com/mrlkn/django-redis-session
Project-URL: Documentation, https://github.com/mrlkn/django-redis-session/README.md
Project-URL: Source, https://github.com/mrlkn/django-redis-session
Keywords: django,session,redis
Classifier: Development Status :: 3 - Alpha
Classifier: Intended Audience :: Developers
Classifier: License :: OSI Approved :: MIT License
Classifier: Programming Language :: Python :: 3
Classifier: Programming Language :: Python :: 3.8
Classifier: Programming Language :: Python :: 3.9
Classifier: Programming Language :: Python :: 3.10
License-File: LICENSE
Requires-Dist: django >=3.0
Requires-Dist: redis >=3.5
